tup/__init__.py
tup/tup.py
tup-0.3.dist-info/LICENSE
tup-0.3.dist-info/METADATA
tup-0.3.dist-info/WHEEL
tup-0.3.dist-info/entry_points.txt
tup-0.3.dist-info/top_level.txt
tup-0.3.dist-info/RECORD
