Metadata-Version: 2.1
Name: tup
Version: 0.3
Summary: CLI Telegram file uploder
Home-page: https://github.com/Qwerty-Space/tup
Author: Oliver Duce
Author-email: oliver_duce@live.co.uk
License: UNKNOWN
Platform: UNKNOWN
Classifier: Programming Language :: Python :: 3
Classifier: License :: OSI Approved :: GNU General Public License v3 (GPLv3)
Classifier: Operating System :: OS Independent
Requires-Dist: Telethon (>=1.7)
